sahara_plugin_storm/__init__.py
sahara_plugin_storm/i18n.py
sahara_plugin_storm/locale/de/LC_MESSAGES/sahara_plugin_storm.po
sahara_plugin_storm/locale/en_GB/LC_MESSAGES/sahara_plugin_storm.po
sahara_plugin_storm/locale/id/LC_MESSAGES/sahara_plugin_storm.po
sahara_plugin_storm/locale/ne/LC_MESSAGES/sahara_plugin_storm.po
sahara_plugin_storm/plugins/__init__.py
sahara_plugin_storm/plugins/storm/__init__.py
sahara_plugin_storm/plugins/storm/config_helper.py
sahara_plugin_storm/plugins/storm/edp_engine.py
sahara_plugin_storm/plugins/storm/plugin.py
sahara_plugin_storm/plugins/storm/run_scripts.py
sahara_plugin_storm/tests/__init__.py
sahara_plugin_storm/tests/unit/__init__.py
sahara_plugin_storm/tests/unit/base.py
sahara_plugin_storm/tests/unit/plugins/__init__.py
sahara_plugin_storm/tests/unit/plugins/storm/__init__.py
sahara_plugin_storm/tests/unit/plugins/storm/test_config_helper.py
sahara_plugin_storm/tests/unit/plugins/storm/test_plugin.py
sahara_plugin_storm/utils/__init__.py
sahara_plugin_storm/utils/patches.py
sahara_plugin_storm-10.0.0.dist-info/AUTHORS
sahara_plugin_storm-10.0.0.dist-info/LICENSE
sahara_plugin_storm-10.0.0.dist-info/METADATA
sahara_plugin_storm-10.0.0.dist-info/WHEEL
sahara_plugin_storm-10.0.0.dist-info/entry_points.txt
sahara_plugin_storm-10.0.0.dist-info/pbr.json
sahara_plugin_storm-10.0.0.dist-info/top_level.txt
sahara_plugin_storm-10.0.0.dist-info/RECORD
